pyrtklib5/__init__.py
pyrtklib5/pyrtklib5.pyi
pyrtklib5/Release/pyrtklib5.pyd
pyrtklib5-0.2.8.dist-info/licenses/LICENSE
pyrtklib5-0.2.8.dist-info/METADATA
pyrtklib5-0.2.8.dist-info/WHEEL
pyrtklib5-0.2.8.dist-info/top_level.txt
pyrtklib5-0.2.8.dist-info/RECORD
