Metadata-Version: 2.4
Name: pyrtklib5
Version: 0.2.8
Summary: This is a python binding for rtklib_demo5
Home-page: https://github.com/IPNL-POLYU/pyrtklib_demo5
Author: Runzhi Hu
Author-email: run-zhi.hu@connect.polyu.hk
License-File: LICENSE
Dynamic: author
Dynamic: author-email
Dynamic: description
Dynamic: description-content-type
Dynamic: home-page
Dynamic: license-file
Dynamic: summary
